cfp/VERSION
cfp/__init__.py
cfp/py.typed
cfp/stack_parameters.py
cfp/types.py
cfp/exceptions/__init__.py
cfp/exceptions/no_resolver.py
cfp/exceptions/py.typed
cfp/exceptions/stack_parameters.py
cfp/resolver_factories/__init__.py
cfp/resolver_factories/parameter_store_resolver_factory.py
cfp/resolver_factories/py.typed
cfp/resolver_factories/resolver_factory.py
cfp/resolver_factories/string_resolver_factory.py
cfp/resolver_factories/use_previous_resolver_factory.py
cfp/resolvers/__init__.py
cfp/resolvers/parameter_store_resolver.py
cfp/resolvers/py.typed
cfp/resolvers/resolver.py
cfp/resolvers/string_resolver.py
cfp/resolvers/use_previous_resolver.py
cfp/sources/__init__.py
cfp/sources/parameter_store.py
cfp/sources/py.typed
cfp/sources/source.py
cfp/sources/use_previous.py
cfp-1.1.0.dist-info/LICENSE
cfp-1.1.0.dist-info/METADATA
cfp-1.1.0.dist-info/WHEEL
cfp-1.1.0.dist-info/top_level.txt
cfp-1.1.0.dist-info/RECORD
